Metadata-Version: 2.1
Name: oneNeuron-pypi-Tharunsd23
Version: 0.0.1
Summary: it's an implementation of Perceptron
Home-page: https://github.com/{USER_NAME}/{PROJECT_NAME}
Author: USER_NAME
Author-email: tharunsd23@gmail.com
License: UNKNOWN
Project-URL: Bug Tracker, https://github.com/{USER_NAME}/{PROJECT_NAME}/issues
Platform: UNKNOWN
Classifier: Programming Language :: Python :: 3
Classifier: License :: OSI Approved :: MIT License
Classifier: Operating System :: OS Independent
Requires-Python: >=3.7
License-File: LICENSE
Requires-Dist: numpy
Requires-Dist: tqdm
